Workbook

Sheet LISEZ-MOI
A1: Dashboard Aurlom — fichier source des données (mode réel)
A3: PRINCIPE
A4: Ce classeur est l'unique source de données du dashboard. Chaque onglet est une table plate : en-têtes en ligne 1, une ligne = un enregistrement.
A5: Les valeurs en BLEU sont à saisir/mettre à jour. Les valeurs préremplies sont les données de démonstration : elles montrent le format attendu, remplacez-les par vos chiffres réels.
A7: RÈGLES (contrat avec le dashboard — à respecter strictement)
A8: 1. Ne jamais renommer les onglets ni les en-têtes de colonnes, ne pas fusionner de cellules, ne pas insérer de colonnes.
A9: 2. Unités : montants en k€ sauf mention M€ dans l'en-tête ; pourcentages en nombre (52 = 52 %) ; charges en NÉGATIF (ex. -6 780).
A10: 3. Dates au format date Excel (affichées mmm-aa). Ne pas saisir de texte dans une colonne de dates ou de nombres.
A11: 4. Une cellule de montant vide dans echeances_lbo = livrable documentaire (badge « doc »).
A12: 5. Le dashboard calcule lui-même : totaux, cumuls, marges, croissances vs N-1, moyenne 12M, remplissage, ratios. Ne saisir que le brut.
A13: 6. L'onglet controles vérifie la cohérence (sommes campus vs groupe, etc.) : tout doit afficher OK avant d'importer le fichier.
A15: CONTENU
... A19: previsionnel / hypotheses / points_cles — projections 12 mois par scénario · controles — vérifications automatiques

Sheet parametres
A1: cle | B1: valeur
A2: exercice_libelle | B2: 2025-26
A3: ltm_debut | B3: 45839
A4: ltm_fin | B4: 46174
A5: date_maj | B5: 46205

Sheet mensuel_groupe
A1: mois | B1: ca_reel_keur | C1: ca_budget_keur | D1: ebitda_reel_keur | E1: ebitda_budget_keur | F1: tresorerie_brute_meur | G1: emprunts_meur | H1: creances_opco_meur | I1: dso_opco_jours
A2: 45474 | B2: 714 | C2: 703 | D2: -141 | E2: -137 | F2: 1.65 | G2: 9.6 | H2: 1.3 | I2: 61
A3: 45505 | B3: 540 | C3: 532 | D3: -247 | E3: -240 | F3: 1.5 | G3: 9.6 | H3: 1.28 | I3: 61
A4: 45536 | B4: 2244 | C4: 2210 | D4: 687 | E4: 666 | F4: 1.9 | G4: 9.6 | H4: 1.45 | I4: 63
A5: 45566 | B5: 2024 | C5: 1994 | D5: 493 | E5: 478 | F5: 2.1 | G5: 9.55 | H5: 1.55 | I5: 64
A6: 45597 | B6: 1447 | C6: 1425 | D6: 211 | E6: 205 | F6: 1.85 | G6: 9.55 | H6: 1.6 | I6: 65
A7: 45627 | B7: 1364 | C7: 1344 | D7: 167 | E7: 162 | F7: 1.9 | G7: 9.55 | H7: 1.55 | I7: 65
A8: 45658 | B8: 1813 | C8: 1786 | D8: 370 | E8: 359 | F8: 2.05 | G8: 9.45 | H8: 1.5 | I8: 64
A9: 45689 | B9: 1612 | C9: 1588 | D9: 273 | E9: 265 | F9: 1.95 | G9: 9.45 | H9: 1.52 | I9: 64
A10: 45717 | B10: 1548 | C10: 1525 | D10: 247 | E10: 240 | F10: 1.9 | G10: 9.45 | H10: 1.55 | I10: 65
A11: 45748 | B11: 1575 | C11: 1551 | D11: 264 | E11: 256 | F11: 1.85 | G11: 9.3 | H11: 1.58 | I11: 65
A12: 45778 | B12: 1676 | C12: 1651 | D12: 300 | E12: 291 | F12: 2 | G12: 9.3 | H12: 1.58 | I12: 65
A13: 45809 | B13: 1566 | C13: 1543 | D13: 256 | E13: 248 | F13: 2.15 | G13: 9.3 | H13: 1.6 | I13: 65
... A25: 46174 | B25: 1710 | C25: 1680 | D25: 290 | E25: 279 | F25: 2.45 | G25: 8.4 | H25: 1.92 | I25: 74

Sheet pnl_ltm
A1: poste | B1: montant_keur | C1: montant_n1_keur
A2: ca_alternance_opco | B2: 10610 | C2: 9465
A3: ca_scolarite_initiale | B3: 7450 | C3: 7042
A4: ca_stages_prepas | B4: 1730 | C4: 1673
A5: couts_pedagogiques | B5: -6780 | C5: -6141
A6: masse_salariale_support | B6: -4320 | C6: -4072
A7: loyers_campus | B7: -2810 | C7: -2731
A8: marketing_admissions | B8: -1590 | C8: -1345
A9: autres_opex | B9: -1020 | C9: -981

Sheet tresorerie_13s
A1: semaine | B1: solde_reel_meur | C1: solde_projete_meur
A2: S23 | B2: 2.18
A3: S24 | B3: 2.31
A4: S25 | B4: 2.24
A5: S26 | B5: 2.45 | C5: 2.45
A6: S27 | C6: 2.38
A7: S28 | C7: 2.12
A8: S29 | C8: 1.86
A9: S30 | C9: 1.94
A10: S31 | C10: 1.71
A11: S32 | C11: 1.52
A12: S33 | C12: 1.44
A13: S34 | C13: 1.68
A14: S35 | C14: 2.05
A15: S36 | C15: 2.62
A16: S37 | C16: 3.18
A17: S38 | C17: 3.05
A18: S39 | C18: 2.88

Sheet covenants
A1: nom | B1: valeur | C1: seuil | D1: sens
A2: Levier net (DN/EBITDA) | B2: 1.8 | C2: 2 | D2: <
A3: DSCR (CF libre / service dette) | B3: 1.6 | C3: 1 | D3: >

Sheet echeances_lbo
A1: libelle | B1: date | C1: montant_keur
A2: Reporting T2 2026 (J+60) | B2: 46265
A3: Attestation ratios 30/06/2026 | B3: 46280
A4: Demande waiver capex | B4: 46295
A5: Service dette T3 | B5: 46295 | C5: 340

Sheet inscriptions
A1: mois | B1: rentree_n | C1: rentree_n1
A2: 45870 | B2: 90 | C2: 70
A3: 45901 | B3: 180 | C3: 150
A4: 45931 | B4: 230 | C4: 190
A5: 45962 | B5: 290 | C5: 240
A6: 45992 | B6: 400 | C6: 330
A7: 46023 | B7: 460 | C7: 380
A8: 46054 | B8: 780 | C8: 690
A9: 46082 | B9: 1240 | C9: 1080
A10: 46113 | B10: 1690 | C10: 1470
A11: 46143 | B11: 2080 | C11: 1820
A12: 46174 | B12: 2210 | C12: 2210
A13: 46204 | C13: 2540
A14: 46235 | C14: 2700
A15: 46266 | C15: 2810

Sheet filieres_groupe
A1: filiere | B1: etudiants
A2: BTS MCO | B2: 420
A3: BTS NDRC | B3: 380
A4: BTS CG | B4: 260
A5: BTS CI | B5: 240
A6: BTS PI | B6: 210
A7: Autres BTS | B7: 350
A8: Bachelors | B8: 250
A9: Prépas | B9: 700

Sheet acquisition
A1: indicateur | B1: valeur | C1: variation_n1
A2: Leads qualifiés | B2: 11 240 | C2: +8 %
A3: Taux de conversion | B3: 14,2 % | C3: +1,1 pt
A4: CAC moyen | B4: 132 € | C4: +11 €
A5: CA moyen / étudiant | B5: 6 550 € | C5: +2,6 %
A6: CA / CAC par étudiant | B6: 49,6× | C6: +1,2×

Sheet campus
A1: campus_id | B1: nom | C1: adresse | D1: capacite | E1: etudiants | F1: pct_alternance | G1: reussite_bts_pct | H1: effectif_moyen_classe | I1: attrition_pct | J1: nps | K1: cout_prof_keur | L1: loyer_annuel_keur | M1: surface_m2
A2: roquette | B2: Paris — Roquette | C2: 48 rue de la Roquette, 75011 | D2: 850 | E2: 780 | F2: 52 | G2: 96 | H2: 20 | I2: 3.8 | J2: 64 | K2: 61 | L2: 610 | M2: 1450
A3: parmentier | B3: Paris — Parmentier | C3: 16 avenue Parmentier, 75011 | D3: 500 | E3: 420 | F3: 55 | G3: 95 | H3: 19 | I3: 4.2 | J3: 61 | K3: 59 | L3: 340 | M3: 820
A4: sentier | B4: Paris — Sentier | C4: quartier Sentier, 75002 | D4: 380 | E4: 310 | F4: 58 | G4: 94 | H4: 18 | I4: 4.5 | J4: 59 | K4: 58 | L4: 295 | M4: 610
A5: jaures | B5: Paris — Jaurès | C5: 118 avenue Jean-Jaurès, 75019 | D5: 450 | E5: 360 | F5: 56 | G5: 93 | H5: 19 | I5: 4.9 | J5: 58 | K5: 58 | L5: 285 | M5: 740
A6: belair | B6: Paris — Bel-Air | C6: quartier Bel-Air, 75012 | D6: 350 | E6: 290 | F6: 54 | G6: 94 | H6: 18 | I6: 4.4 | J6: 60 | K6: 57 | L6: 250 | M6: 560
A7: boulogne | B7: Boulogne | C7: 59 rue de Billancourt, 92100 | D7: 320 | E7: 240 | F7: 51 | G7: 92 | H7: 17 | I7: 5.2 | J7: 57 | K7: 56 | L7: 230 | M7: 520
A8: lille | B8: Lille | C8: centre-ville, Lille | D8: 300 | E8: 220 | F8: 49 | G8: 91 | H8: 16 | I8: 5.8 | J8: 55 | K8: 54 | L8: 175 | M8: 480
A9: nice | B9: Nice | C9: ICONIC, gare de Nice | D9: 260 | E9: 190 | F9: 47 | G9: 90 | H9: 15 | I9: 6.1 | J9: 54 | K9: 54 | L9: 168 | M9: 430

Sheet campus_mensuel
A1: campus_id | B1: mois | C1: ca_keur
A2: roquette | B2: 45839 | C2: 226
A3: roquette | B3: 45870 | C3: 171
A4: roquette | B4: 45901 | C4: 733
A5: roquette | B5: 45931 | C5: 662
A6: roquette | B6: 45962 | C6: 474
A7: roquette | B7: 45992 | C7: 447
A8: roquette | B8: 46023 | C8: 590
A9: roquette | B9: 46054 | C9: 524
A10: roquette | B10: 46082 | C10: 507
A11: roquette | B11: 46113 | C11: 513
A12: roquette | B12: 46143 | C12: 546
A13: roquette | B13: 46174 | C13: 122
... A97: nice | B97: 46174 | C97: 29

Sheet campus_pnl
A1: campus_id | B1: ca_alternance | C1: ca_initiale | D1: ca_stages_prepas | E1: couts_pedagogiques | F1: masse_salariale_support | G1: loyers | H1: marketing_admissions | I1: autres_opex
A2: roquette | B2: 2956 | C2: 2079 | D2: 480 | E2: -1892 | F2: -1014 | G2: -610 | H2: -441 | I2: -303
A3: parmentier | B3: 1584 | C3: 1114 | D3: 257 | E3: -1014 | F3: -672 | G3: -340 | H3: -236 | I3: -163
A4: sentier | B4: 1168 | C4: 822 | D4: 190 | E4: -748 | F4: -498 | G4: -295 | H4: -174 | I4: -120
A5: jaures | B5: 1359 | C5: 956 | D5: 220 | E5: -870 | F5: -613 | G5: -285 | H5: -203 | I5: -139
A6: belair | B6: 1093 | C6: 769 | D6: 178 | E6: -700 | F6: -515 | G6: -250 | H6: -163 | I6: -112
A7: boulogne | B7: 906 | C7: 637 | D7: 147 | E7: -580 | F7: -457 | G7: -230 | H7: -135 | I7: -93
A8: lille | B8: 828 | C8: 582 | D8: 135 | E8: -530 | F8: -496 | G8: -175 | H8: -124 | I8: -85
A9: nice | B9: 713 | C9: 501 | D9: 116 | E9: -456 | F9: -442 | G9: -168 | H9: -106 | I9: -73

Sheet previsionnel
A1: scenario | B1: mois | C1: ca_keur | D1: ebitda_keur | E1: tresorerie_meur
A2: base | B2: 46204 | C2: 820 | D2: -160 | E2: 2.4
A3: base | B3: 46235 | C3: 610 | D3: -280 | E3: 1.9
A4: base | B4: 46266 | C4: 2680 | D4: 780 | E4: 2.6
A5: base | B5: 46296 | C5: 2390 | D5: 560 | E5: 3.4
A6: base | B6: 46327 | C6: 1710 | D6: 240 | E6: 2.9
A7: base | B7: 46357 | C7: 1620 | D7: 190 | E7: 3.3
A8: base | B8: 46388 | C8: 2140 | D8: 420 | E8: 4.1
A9: base | B9: 46419 | C9: 1900 | D9: 310 | E9: 4.3
A10: base | B10: 46447 | C10: 1830 | D10: 280 | E10: 4.4
A11: base | B11: 46478 | C11: 1860 | D11: 300 | E11: 4.6
A12: base | B12: 46508 | C12: 1980 | D12: 340 | E12: 4.9
A13: base | B13: 46539 | C13: 1850 | D13: 290 | E13: 5
... A37: haut | B37: 46539 | C37: 2040 | D37: 400 | E37: 6.6

Sheet hypotheses
A1: scenario | B1: ordre | C1: texte
A2: base | B2: 1 | C2: Rentrée sept. 2026 : 2 990 étudiants (+6 %)
A3: base | B3: 2 | C3: NPEC stables
A4: base | B4: 3 | C4: Tarifs initiale : +2 %
A5: base | B5: 4 | C5: Attrition : 4,8 %
A6: base | B6: 5 | C6: Ouverture campus : 1
A7: bas | B7: 1 | C7: Rentrée sept. 2026 : 2 690 étudiants (−10 % vs base)
A8: bas | B8: 2 | C8: NPEC stables
A9: bas | B9: 3 | C9: Tarifs inchangés
A10: bas | B10: 4 | C10: Attrition : 5,5 %
A11: bas | B11: 5 | C11: Ouverture campus : 1 (décalée à janv. 27)
A12: haut | B12: 1 | C12: Rentrée sept. 2026 : 3 290 étudiants (+10 % vs base)
A13: haut | B13: 2 | C13: NPEC stables
... A16: haut | B16: 5 | C16: Ouverture campus : 1

Sheet points_cles
A1: numero | B1: mois | C1: texte
A2: 1 | B2: 46235 | C2: Service de la dette (annuité) : (1,5) M€ — creux d'août 26
A3: 2 | B3: 46296 | C3: Encaissements rentrée (scolarité + acomptes) — pic sept.-oct. 26
A4: 3 | B4: 46327 | C4: Liquidation IS : (0,6) M€ — creux de nov. 26
A5: 4 | B5: 46388 | C5: Premiers versements NPEC rentrée — janv.-févr. 27

Sheet controles
A1: controle | B1: valeur_a | C1: valeur_b | D1: ecart | E1: statut
A2: CA groupe LTM : mensuel vs P&L | B2: =SUM(mensuel_groupe!B14:B25) -> 19790 | C2: =SUM(pnl_ltm!B2:B4) -> 19790 | D2: =B2-C2 -> 0 | E2: =IF(ABS(D2)<=1,"OK","ÉCART") -> OK
A3: CA groupe LTM : mensuel vs somme campus | B3: =SUM(mensuel_groupe!B14:B25) -> 19790 | C3: =SUM(campus_pnl!B2:D9) -> 19790 | D3: =B3-C3 -> 0 | E3: =IF(ABS(D3)<=1,"OK","ÉCART") -> OK
A4: EBITDA groupe LTM : mensuel vs P&L | B4: =SUM(mensuel_groupe!D14:D25) -> 3270 | C4: =SUM(pnl_ltm!B2:B9) -> 3270 | D4: =B4-C4 -> 0 | E4: =IF(ABS(D4)<=1,"OK","ÉCART") -> OK
A5: EBITDA groupe LTM : mensuel vs somme campus | B5: =SUM(mensuel_groupe!D14:D25) -> 3270 | C5: =SUM(campus_pnl!B2:I9) -> 3270 | D5: =B5-C5 -> 0 | E5: =IF(ABS(D5)<=1,"OK","ÉCART") -> OK
A6: Étudiants : somme campus vs somme filières | B6: =SUM(campus!E2:E9) -> 2810 | C6: =SUM(filieres_groupe!B2:B9) -> 2810 | D6: =B6-C6 -> 0 | E6: =IF(ABS(D6)<=1,"OK","ÉCART") -> OK
A7: CA campus : référentiel vs somme campus_mensuel | B7: =SUM(campus_pnl!B2:D9) -> 19790 | C7: =SUM(campus_mensuel!C2:C97) -> 19790 | D7: =B7-C7 -> 0 | E7: =IF(ABS(D7)<=1,"OK","ÉCART") -> OK
A9: Tous les statuts doivent être OK (tolérance d'arrondi : 1 k€) avant import dans le dashboard.
